cabrillo/__init__.py
cabrillo/cabrillo.py
cabrillo/data.py
cabrillo/errors.py
cabrillo/parser.py
cabrillo/qso.py
cabrillo-0.2.1.dist-info/LICENSE
cabrillo-0.2.1.dist-info/METADATA
cabrillo-0.2.1.dist-info/WHEEL
cabrillo-0.2.1.dist-info/top_level.txt
cabrillo-0.2.1.dist-info/RECORD
