Metadata-Version: 2.1
Name: cabrillo
Version: 0.2.1
Summary: A Python library to parse Cabrillo-format amateur radio contest logs.
Home-page: https://github.com/thxo/cabrillo
Author: thxo
Author-email: thxo@riseup.net
Classifier: Programming Language :: Python :: 3
Classifier: License :: OSI Approved :: BSD License
Classifier: Operating System :: OS Independent
Classifier: Topic :: Communications :: Ham Radio
License-File: LICENSE
